LICENSE
MANIFEST.in
README.md
VERSION
setup.cfg
setup.py
src/finaddr/__init__.py
src/finaddr/finaddr.py
src/finaddr.egg-info/PKG-INFO
src/finaddr.egg-info/SOURCES.txt
src/finaddr.egg-info/dependency_links.txt
src/finaddr.egg-info/not-zip-safe
src/finaddr.egg-info/requires.txt
src/finaddr.egg-info/top_level.txt
tests/data/schema.json
tests/data/testdata.csv