Metadata-Version: 2.1
Name: finaddr
Version: 1.1.4
Summary: Library for querying finnish building addresses with coordinates
Home-page: https://github.com/phasi/finaddr
Author: Pasi Talvitie
Author-email: pasi@antispam.com
License: MIT
Keywords: finnish,addresses,buildings,coordinates
Platform: UNKNOWN
Classifier: Programming Language :: Python :: 3
